rayflow/__init__.py
rayflow/simpleagent.py
rayflow/tool.py
rayflow-0.1.0.dist-info/METADATA
rayflow-0.1.0.dist-info/WHEEL
rayflow-0.1.0.dist-info/top_level.txt
rayflow-0.1.0.dist-info/RECORD
